bootstrap.py
buildout.cfg
setup.py
todo.txt
docs/thoughts.txt
src/ore/__init__.py
src/ore.metamime.egg-info/PKG-INFO
src/ore.metamime.egg-info/SOURCES.txt
src/ore.metamime.egg-info/dependency_links.txt
src/ore.metamime.egg-info/namespace_packages.txt
src/ore.metamime.egg-info/not-zip-safe
src/ore.metamime.egg-info/requires.txt
src/ore.metamime.egg-info/top_level.txt
src/ore/metamime/CREDITS.txt
src/ore/metamime/__init__.py
src/ore/metamime/_base.py
src/ore/metamime/configure.zcml
src/ore/metamime/extractor-keys.txt
src/ore/metamime/file.py
src/ore/metamime/generator.py
src/ore/metamime/hachoir-keys.txt
src/ore/metamime/hachoir.py
src/ore/metamime/interfaces.py
src/ore/metamime/libextractor.py
src/ore/metamime/meta.zcml
src/ore/metamime/mimetypes.zcml
src/ore/metamime/readme.txt
src/ore/metamime/todo.txt
src/ore/metamime/utility.py
src/ore/metamime/zcml.py
src/ore/metamime/browser/__init__.py
src/ore/metamime/browser/configure.zcml
src/ore/metamime/browser/icons/archive.png
src/ore/metamime/browser/icons/archive.svg
src/ore/metamime/browser/icons/audio.png
src/ore/metamime/browser/icons/css.png
src/ore/metamime/browser/icons/css.svg
src/ore/metamime/browser/icons/doc.png
src/ore/metamime/browser/icons/doc.svg
src/ore/metamime/browser/icons/file-manager.svg
src/ore/metamime/browser/icons/image.png
src/ore/metamime/browser/icons/image.svg
src/ore/metamime/browser/icons/pdf.png
src/ore/metamime/browser/icons/pdf.svg
src/ore/metamime/browser/icons/spreadsheet.png
src/ore/metamime/browser/icons/spreadsheet.svg
src/ore/metamime/browser/icons/trash-empty.svg
src/ore/metamime/browser/icons/trash-full.svg
src/ore/metamime/tests/__init__.py
src/ore/metamime/tests/_base.py
src/ore/metamime/tests/all.py
src/ore/metamime/tests/test_hachoir.py
src/ore/metamime/tests/test_libextractor.py
src/ore/metamime/tests/data/data.gif
src/ore/metamime/tests/data/data.mp3
src/ore/metamime/tests/data/data.pdf