Metadata-Version: 1.0
Name: ore.metamime
Version: 0.1.4
Summary: Mime Identification and Property Extraction
Home-page: http://pypi.python.org/pypi/ore.metamime
Author: Kapil Thangavelu
Author-email: kapil.foss@gmail.com
License: UNKNOWN
Platform: UNKNOWN
Classifier: Programming Language :: Python
Classifier: Environment :: Web Environment
Classifier: Topic :: Internet :: WWW/HTTP :: WSGI :: Application
Classifier: Framework :: Zope3
